{
  "project_info": {
    "project_number": "890500108241",
    "project_id": "laboratoriska-vezba-4a8c4",
    "storage_bucket": "laboratoriska-vezba-4a8c4.firebasestorage.app"
  },
  "client": [
    {
      "client_info": {
        "mobilesdk_app_id": "1:890500108241:android:0f3a3e708ccda18cc41af0",
        "android_client_info": {
          "package_name": "com.ma193020.lab3"
        }
      },
      "oauth_client": [],
      "api_key": [
        {
          "current_key": "AIzaSyDqIz3-nDVS4jeV1OqIYdjXvJsXAca2iXs"
        }
      ],
      "services": {
        "appinvite_service": {
          "other_platform_oauth_client": []
        }
      }
    }
  ],
  "configuration_version": "1"
}